setup.py
project_cylon/BehaveController.py
project_cylon/CLI.py
project_cylon/CommonSteps.py
project_cylon/CustomOperators.py
project_cylon/Element.py
project_cylon/Logger.py
project_cylon/Page.py
project_cylon/PageFactory.py
project_cylon/Reporter.py
project_cylon/Responsive.py
project_cylon/SiteConfig.py
project_cylon/TestCase.py
project_cylon/TestServer.py
project_cylon/TestSuite.py
project_cylon/World.py
project_cylon/WorldContext.py
project_cylon/__init__.py
project_cylon/behook.py
project_cylon.egg-info/PKG-INFO
project_cylon.egg-info/SOURCES.txt
project_cylon.egg-info/dependency_links.txt
project_cylon.egg-info/entry_points.txt
project_cylon.egg-info/not-zip-safe
project_cylon.egg-info/requires.txt
project_cylon.egg-info/top_level.txt
project_cylon/api/ApiProject.py
project_cylon/api/ApiReport.py
project_cylon/api/ApiRun.py
project_cylon/api/__init__.py
project_cylon/public/test-runner-new.html
project_cylon/public/test-runner.html
project_cylon/public/css/bootstrap.css
project_cylon/public/js/bootstrap.min.js
project_cylon/public/js/jquery-2.1.1.min.js
project_cylon/public/js/navbar.js
project_cylon/public/js/run-panel.js
project_cylon/public/js/test-report.js
project_cylon/public/js/test-runner.js