Metadata-Version: 1.1
Name: project-cylon
Version: 2.1.5
Summary: Generic Web Acceptance Testing Framework
Home-page: https://github.com/gigapixel/project-cylon
Author: BridgeAsia Team
Author-email: gigapixel7@gmail.com
License: MIT
Platform: UNKNOWN
Classifier: Development Status :: 4 - Beta
Classifier: Environment :: Console
Classifier: License :: OSI Approved :: MIT License
Classifier: Operating System :: OS Independent
Classifier: Programming Language :: Python :: 2.7
Classifier: Topic :: Software Development :: Libraries :: Python Modules
Classifier: Topic :: Software Development :: Testing
